flake/__init__.py
flake/_assert.py
flake/afterEach.py
flake/beforeEach.py
flake/capture.py
flake/every.py
flake/group.py
flake/publish.py
flake/shared.py
flake/snap.py
flake/time.py
flake_python-1.0.1.dist-info/LICENSE
flake_python-1.0.1.dist-info/METADATA
flake_python-1.0.1.dist-info/WHEEL
flake_python-1.0.1.dist-info/top_level.txt
flake_python-1.0.1.dist-info/RECORD
